pysafe_config/__init__.py
pysafe_config/_getenv.py
pysafe_config/_helper_bool.py
pysafe_config/_helper_float.py
pysafe_config/_helper_int.py
pysafe_config/_helper_str.py
pysafe_config-0.0.0.dist-info/METADATA
pysafe_config-0.0.0.dist-info/WHEEL
pysafe_config-0.0.0.dist-info/licenses/LICENSE
pysafe_config-0.0.0.dist-info/RECORD
