Metadata-Version: 2.4
Name: pysafe-config
Version: 0.0.0
Summary: Type safe environment variables
License-File: LICENSE
Author: Lancasterg
Author-email: lancaster0180@gmail.com
Requires-Python: >=3.10,<4.0
Classifier: Programming Language :: Python :: 3
Classifier: Programming Language :: Python :: 3.10
Classifier: Programming Language :: Python :: 3.11
Classifier: Programming Language :: Python :: 3.12
Classifier: Programming Language :: Python :: 3.13
Classifier: Programming Language :: Python :: 3.14
